odoo/addons/hr_personal_equipment_stock/README.rst
odoo/addons/hr_personal_equipment_stock/__init__.py
odoo/addons/hr_personal_equipment_stock/__manifest__.py
odoo/addons/hr_personal_equipment_stock/i18n/es.po
odoo/addons/hr_personal_equipment_stock/i18n/es_PA.po
odoo/addons/hr_personal_equipment_stock/i18n/hr_personal_equipment_stock.pot
odoo/addons/hr_personal_equipment_stock/i18n/it.po
odoo/addons/hr_personal_equipment_stock/models/__init__.py
odoo/addons/hr_personal_equipment_stock/models/hr_personal_equipment.py
odoo/addons/hr_personal_equipment_stock/models/hr_personal_equipment_request.py
odoo/addons/hr_personal_equipment_stock/models/procurement_group.py
odoo/addons/hr_personal_equipment_stock/models/stock_location.py
odoo/addons/hr_personal_equipment_stock/models/stock_move.py
odoo/addons/hr_personal_equipment_stock/models/stock_picking.py
odoo/addons/hr_personal_equipment_stock/models/stock_rule.py
odoo/addons/hr_personal_equipment_stock/readme/CONFIGURE.rst
odoo/addons/hr_personal_equipment_stock/readme/CONTRIBUTORS.rst
odoo/addons/hr_personal_equipment_stock/readme/CREDITS.rst
odoo/addons/hr_personal_equipment_stock/readme/DESCRIPTION.rst
odoo/addons/hr_personal_equipment_stock/readme/INSTALL.rst
odoo/addons/hr_personal_equipment_stock/readme/USAGE.rst
odoo/addons/hr_personal_equipment_stock/static/description/icon.png
odoo/addons/hr_personal_equipment_stock/static/description/index.html
odoo/addons/hr_personal_equipment_stock/tests/__init__.py
odoo/addons/hr_personal_equipment_stock/tests/test_hr_personal_equipment_stock.py
odoo/addons/hr_personal_equipment_stock/views/hr_personal_equipment.xml
odoo/addons/hr_personal_equipment_stock/views/hr_personal_equipment_request.xml
odoo/addons/hr_personal_equipment_stock/views/procurement_group.xml
odoo/addons/hr_personal_equipment_stock/views/stock_location.xml
odoo/addons/hr_personal_equipment_stock/views/stock_move.xml
odoo/addons/hr_personal_equipment_stock/views/stock_picking.xml
odoo_addon_hr_personal_equipment_stock-16.0.1.0.0.3.dist-info/METADATA
odoo_addon_hr_personal_equipment_stock-16.0.1.0.0.3.dist-info/WHEEL
odoo_addon_hr_personal_equipment_stock-16.0.1.0.0.3.dist-info/top_level.txt
odoo_addon_hr_personal_equipment_stock-16.0.1.0.0.3.dist-info/RECORD
