Metadata-Version: 2.1
Name: odoo-addon-hr_personal_equipment_stock
Version: 16.0.1.0.0.3
Summary: This addon allows to integrate hr_personal_equipment_request with stock
Home-page: https://github.com/OCA/hr
Author: Creu Blanca,Odoo Community Association (OCA)
Author-email: support@odoo-community.org
License: AGPL-3
Classifier: Programming Language :: Python
Classifier: Framework :: Odoo
Classifier: Framework :: Odoo :: 16.0
Classifier: License :: OSI Approved :: GNU Affero General Public License v3
Requires-Python: >=3.10
Requires-Dist: odoo-addon-hr-personal-equipment-request<16.1dev,>=16.0dev
Requires-Dist: odoo<16.1dev,>=16.0a
